16bit_alu.v
module alu (
    input wire [15:0] A,      // First 16-bit operand
    input wire [15:0] B,      // Second 16-bit operand
    input wire [2:0] Op,      // 3-bit operation select
    output reg [15:0] Y,      // 16-bit result
    output reg C,             // Carry/Borrow flag
    output reg V,             // Overflow flag
    output reg N,             // Negative flag
    output reg Z              // Zero flag
);

    reg [16:0] temp;          // Temporary 17-bit result for arithmetic ops

initial begin
$dumpfile("alu.vcd");
$dumpvars(0,alu);
end
    always @(*) begin
        case (Op)
            3'b000: begin // Addition
                temp = A + B;
                Y = temp[15:0];
                C = temp[16];              // Carry out
                V = (A[15] & B[15] & ~Y[15]) | (~A[15] & ~B[15] & Y[15]); // Overflow
            end
            3'b001: begin // Subtraction
                temp = A - B;
                Y = temp[15:0];
                C = (A < B);               // Borrow (1 if A < B)
                V = (A[15] & ~B[15] & ~Y[15]) | (~A[15] & B[15] & Y[15]); // Overflow
            end
            3'b010: begin // AND
                Y = A & B;
                C = 1'b0;
                V = 1'b0;
            end
            3'b011: begin // OR
                Y = A | B;
                C = 1'b0;
                V = 1'b0;
            end
            3'b100: begin // XOR
                Y = A ^ B;
                C = 1'b0;
                V = 1'b0;
            end
            3'b101: begin // NOT
                Y = ~A;
                C = 1'b0;
                V = 1'b0;
            end
            3'b110: begin // Left Shift by 1
                Y = A << 1;
                C = A[15];                 // Carry is MSB
                V = 1'b0;
            end
            3'b111: begin // Arithmetic Right Shift by 1
                Y = {A[15], A[15:1]};     // Sign-extended right shift
                C = A[0];                  // Carry is LSB
                V = 1'b0;
            end
            default: begin
                Y = 16'b0;
                C = 1'b0;
                V = 1'b0;
            end
        endcase
        N = Y[15];                         // Negative flag (sign bit)
        Z = (Y == 16'b0);                  // Zero flag
    end
endmodule

alu.vcd
$date
	Tue Mar  4 22:09:36 2025
$end
$version
	Icarus Verilog
$end
$timescale
	1ps
$end
$scope module alu $end
$var wire 16 ! A [15:0] $end
$var wire 16 " B [15:0] $end
$var wire 3 # Op [2:0] $end
$var reg 1 $ C $end
$var reg 1 % N $end
$var reg 1 & V $end
$var reg 16 ' Y [15:0] $end
$var reg 1 ( Z $end
$var reg 17 ) temp [16:0] $end
$upscope $end
$enddefinitions $end
#0
$dumpvars
b1011100010000101 )
0(
b1011100010000101 '
0&
1%
0$
b0 #
b1010010101010101 "
b1001100110000 !
$end
#1000
0%
1$
b11000011000 '
b10000011000011000 )
b1101000001010111 "
b11010111000001 !
#2000
1%
1&
0$
b1010000001011101 '
b1010000001011101 )
b111101001000000 "
b10011000011101 !
#3000
0%
0&
1$
b10101011010 '
b10000010101011010 )
b101111001000110 "
b1010011100010100 !
#4000
1&
b111000010101101 '
b10111000010101101 )
b1000100001001100 "
b1110100001100001 !
#5000
1%
0$
b1110000010111110 '
b1110000010111110 )
b111110101101101 "
b110001101010001 !
#6000
0&
b1100111011101001 '
b1100111011101001 )
b1001101001010101 "
b11010010010100 !
#7000
0%
b101100110011100 '
b101100110011100 )
b11000001001111 "
b10100101001101 !
#8000
1$
b101100011100111 '
b10101100011100111 )
b1101111111100010 "
b111100100000101 !
#9000
b11011000001001 '
b10011011000001001 )
b111111110101101 "
b1011011001011100 !
#10000
1&
0$
b10100111011010 '
b10100111011010 )
b1 #
b101101000001001 "
b1000001111100011 !
#11000
1%
0&
1$
b1100000000101110 '
b11100000000101110 )
b111000000000010 "
b11000000110000 !
#12000
b1010011000100100 '
b11010011000100100 )
b1111001010101100 "
b1001100011010000 !
#13000
0%
0$
b10000011011101 '
b10000011011101 )
b10100000001100 "
b100100011101001 !
#14000
1%
1&
1$
b1000001011000011 '
b11000001011000011 )
b1010100000011011 "
b10101011011110 !
#15000
0&
0$
b1110010001001011 '
b1110010001001011 )
b1100110100110 "
b1111110111110001 !
#16000
0%
1&
b110100010011100 '
b110100010011100 )
b100001110011100 "
b1010110000111000 !
#17000
0&
b1010010110110 '
b1010010110110 )
b11011110001101 "
b100110001000011 !
#18000
1%
b1110101111100100 '
b1110101111100100 )
b111111011000 "
b1111101110111100 !
#19000
0%
b101110011010001 '
b101110011010001 )
b1000001010110111 "
b1101111110001000 !
#20000
b10010000000100 '
b10 #
b110011100010100 "
b1010110000001111 !
#21000
1%
b1000000000000000 '
b1011001000000110 "
b1100100010000000 !
#22000
0%
b100100000 '
b1010000110110100 "
b100101100101011 !
#23000
1%
b1000101001000010 '
b1010101011000011 "
b1000101001110010 !
#24000
0%
b10001001001100 '
b10011111101110 "
b1111101001011101 !
#25000
1%
b1100000000000000 '
b1111011001100101 "
b1100100110000010 !
#26000
b1000101000000000 '
b1110101110000000 "
b1001111000011110 !
#27000
b1000000110000110 '
b1000101110100110 "
b1001000111011111 !
#28000
0%
b1000010000100 '
b1000010010100 "
b1101001111001110 !
#29000
1%
b1000010110000000 '
b1000010110001000 "
b1110011111100111 !
#30000
b1111100101111110 '
b11 #
b11100001011110 "
b1110100100111100 !
#31000
0%
b111111111111110 '
b110101001111010 "
b11011110001110 !
#32000
b101100111111111 '
b1100010011011 "
b100100101101111 !
#33000
1%
b1101111101011110 '
b101111001010010 "
b1000100101001100 !
#34000
0%
b111111010101111 '
b111111010001101 "
b110010100011 !
#35000
1%
b1101111111110100 '
b111010100000 "
b1101100101010100 !
#36000
b1110111101011111 '
b1110010101010100 "
b1110111101011011 !
#37000
0%
b101111111101111 '
b101111011101100 "
b100101100001011 !
#38000
1%
b1101010111010000 '
b101010110000000 "
b1101010101010000 !
#39000
b1111111011111111 '
b1111101010110110 "
b10010001001101 !
#40000
b1110000010000011 '
b100 #
b1011100110100000 "
b101100100100011 !
#41000
0%
b101000 '
b1101110001100100 "
b1101110001001100 !
#42000
b101000001100110 '
b111110110101010 "
b10110111001100 !
#43000
b101110101110100 '
b1000011010011100 "
b1101101111101000 !
#44000
1%
b1100110110001111 '
b11101010100001 "
b1111011100101110 !
#45000
b1110101110111010 '
b110000001010 "
b1110011110110000 !
#46000
0%
b111101000001110 '
b100100100101000 "
b11001100100110 !
#47000
1%
b1111010011110011 '
b111001010111001 "
b1000011001001010 !
#48000
b1101001000011110 '
b1011001111111010 "
b110000111100100 !
#49000
0%
b111100011101100 '
b1110100001000100 "
b1001000010101000 !
#50000
b11000110000010 '
b101 #
b1110111111101100 "
b1100111001111101 !
#51000
b110010011100100 '
b1010101001010100 "
b1001101100011011 !
#52000
b1110111011101 '
b1011001001110101 "
b1110001000100010 !
#53000
1%
b1010110100000011 '
b1110111000100110 "
b101001011111100 !
#54000
b1000101110011111 '
b10111110010001 "
b111010001100000 !
#55000
0%
b10101111010011 '
b101011111110110 "
b1101010000101100 !
#56000
b1101111101111 '
b100001111101001 "
b1110010000010000 !
#57000
1%
b1110100101110010 '
b1001110110011001 "
b1011010001101 !
#58000
0%
b111011111100101 '
b1011010010100110 "
b1000100000011010 !
#59000
1%
b1011101011110111 '
b11101010110 "
b100010100001000 !
#60000
b1100100101100010 '
b110 #
b110110101111110 "
b110010010110001 !
#61000
1$
b1111001100011010 '
b1000000101001101 "
b1111100110001101 !
#62000
0%
b11001010100010 '
b1001111101001000 "
b1001100101010001 !
#63000
b101101100010100 '
b110000111010 "
b1010110110001010 !
#64000
1%
b1111010110111000 '
b1110101001011111 "
b1111101011011100 !
#65000
0$
b1001111111110110 '
b10010000000100 "
b100111111111011 !
#66000
1$
b1110111100111100 '
b11101010010 "
b1111011110011110 !
#67000
0%
0$
b101110011001110 '
b101000011001011 "
b10111001100111 !
#68000
b100110000111000 '
b1011101000111110 "
b10011000011100 !
#69000
1%
1$
b1111100001101100 '
b1001000100110111 "
b1111110000110110 !
#70000
0%
b11101000001001 '
b111 #
b110101111011101 "
b111010000010011 !
#71000
b11100100100010 '
b101010110001011 "
b111001001000101 !
#72000
0$
b11101111011000 '
b1100110010111000 "
b111011110110000 !
#73000
1%
b1111011010100011 '
b1010001000101100 "
b1110110101000110 !
#74000
b1100111010110001 '
b1000101010111011 "
b1001110101100010 !
#75000
1$
b1110100011010101 '
b1010001010111 "
b1101000110101011 !
#76000
0%
b11101101010111 '
b1111010110000011 "
b111011010101111 !
#77000
b1011010001110 '
b1110110111110 "
b10110100011101 !
#78000
0$
b11100000111 '
b111000000100000 "
b111000001110 !
#79000
1%
1$
b1100001111101010 '
b111011001100101 "
b1000011111010101 !
